pytest_utils/__init__.py
pyteal_utils-0.2.0.dist-info/LICENSE
pyteal_utils-0.2.0.dist-info/METADATA
pyteal_utils-0.2.0.dist-info/WHEEL
pyteal_utils-0.2.0.dist-info/top_level.txt
pyteal_utils-0.2.0.dist-info/RECORD
