Metadata-Version: 2.1
Name: pyteal-utils
Version: 0.2.0
Summary: Utilities to help in the development of PyTeal contracts for Algorand.
Home-page: UNKNOWN
Author: Garrin McGoldrick
Author-email: garrin.mcgoldrick@gmail.com
License: UNKNOWN
Platform: UNKNOWN
Classifier: Programming Language :: Python :: 3
Classifier: License :: OSI Approved :: MIT License
Classifier: Operating System :: POSIX :: Linux
Requires-Python: >=3.6
License-File: LICENSE
